{"title":"Big Black T-Girl Cock","uid":4485639,"size":1469319032,"categoryP":"porn","categoryS":"movies","magnet":"?xt=urn:btih:006c2f93e187eb5d29c84c802aca6aa84a266304&amp;dn=Big+Black+T-Girl+Cock&amp;tr=udp%3A%2F%2Ftracker.openbittorrent.com%3A80&amp;tr=udp%3A%2F%2Fopen.demonii.com%3A1337&amp;tr=udp%3A%2F%2Ftracker.coppersurfer.tk%3A6969&amp;tr=udp%3A%2F%2Fexodus.desync.com%3A6969","seeders":0,"leechers":1,"uploader":"theo1981","files":4,"time":1225750528,"description":"5 Hot Scenes","torrent":{"xt":"urn:btih:006c2f93e187eb5d29c84c802aca6aa84a266304","amp;dn":"Big+Black+T-Girl+Cock","amp;tr":["udp%3A%2F%2Ftracker.openbittorrent.com%3A80","udp%3A%2F%2Fopen.demonii.com%3A1337","udp%3A%2F%2Ftracker.coppersurfer.tk%3A6969","udp%3A%2F%2Fexodus.desync.com%3A6969"],"infoHash":"006c2f93e187eb5d29c84c802aca6aa84a266304","infoHashBuffer":{"type":"Buffer","data":[0,108,47,147,225,135,235,93,41,200,76,128,42,202,106,168,74,38,99,4]},"announce":[],"urlList":[]}}