{"title":"www.boobcamp2000.com.Audree.XXX.[AllSets][GoldenPirates]","uid":6502662,"size":64345151,"categoryP":"porn","categoryS":"pictures","magnet":"?xt=urn:btih:1495d10cc59f3e22dd40ea5f94ad6bb68ce277dd&amp;dn=www.boobcamp2000.com.Audree.XXX.%5BAllSets%5D%5BGoldenPirates%5D&amp;tr=udp%3A%2F%2Ftracker.openbittorrent.com%3A80&amp;tr=udp%3A%2F%2Fopen.demonii.com%3A1337&amp;tr=udp%3A%2F%2Ftracker.coppersurfer.tk%3A6969&amp;tr=udp%3A%2F%2Fexodus.desync.com%3A6969","seeders":0,"leechers":1,"uploader":"GoldenPirates","files":-1,"time":1309303500,"description":"Another torrent from goldenpirates.org\n\nno viruses, no shit, no Bullshit, just pure PORN!\n\nSite:                                                                    &lt;a href=&quot;\nhttp://www.boobcamp2000.com&quot; rel=&quot;nofollow&quot; target=&quot;_NEW&quot;&gt;\nhttp://www.boobcamp2000.com&lt;/a&gt;\n\nTeam:                                                                    &lt;a href=&quot;\nhttp://goldenpirates.org&quot; rel=&quot;nofollow&quot; target=&quot;_NEW&quot;&gt;\nhttp://goldenpirates.org&lt;/a&gt;\n\nUploader/Ripper: blankStare\n\n\n\nMore Golden releases here:                                                                    &lt;a href=&quot;\nhttp://thepiratebay.se/user/Goldenpirates&quot; rel=&quot;nofollow&quot; target=&quot;_NEW&quot;&gt;\nhttp://thepiratebay.se/user/Goldenpirates&lt;/a&gt;\nand here:                                                                    &lt;a href=&quot;\nhttp://blog.goldenpirates.org/&quot; rel=&quot;nofollow&quot; target=&quot;_NEW&quot;&gt;\nhttp://blog.goldenpirates.org/&lt;/a&gt;\n\nEnjoy! \n\nPreviews are in the torrent ...\t","torrent":{"xt":"urn:btih:1495d10cc59f3e22dd40ea5f94ad6bb68ce277dd","amp;dn":"www.boobcamp2000.com.Audree.XXX.%5BAllSets%5D%5BGoldenPirates%5D","amp;tr":["udp%3A%2F%2Ftracker.openbittorrent.com%3A80","udp%3A%2F%2Fopen.demonii.com%3A1337","udp%3A%2F%2Ftracker.coppersurfer.tk%3A6969","udp%3A%2F%2Fexodus.desync.com%3A6969"],"infoHash":"1495d10cc59f3e22dd40ea5f94ad6bb68ce277dd","infoHashBuffer":{"type":"Buffer","data":[20,149,209,12,197,159,62,34,221,64,234,95,148,173,107,182,140,226,119,221]},"announce":[],"urlList":[]}}