{"title":"[Synth] Front 242 - Integration Eight X Ten","uid":3638792,"size":2359378050,"categoryP":"video","categoryS":"music_videos","magnet":"?xt=urn:btih:1fcf1a2d6ebef782f9cffcd458cb016540336542&amp;dn=%5BSynth%5D+Front+242+-+Integration+Eight+X+Ten&amp;tr=udp%3A%2F%2Ftracker.openbittorrent.com%3A80&amp;tr=udp%3A%2F%2Fopen.demonii.com%3A1337&amp;tr=udp%3A%2F%2Ftracker.coppersurfer.tk%3A6969&amp;tr=udp%3A%2F%2Fexodus.desync.com%3A6969","seeders":0,"leechers":2,"uploader":"Memorabilia","files":4,"time":1173825940,"description":"DVD-R\nFrom VHS\nWith covers","torrent":{"xt":"urn:btih:1fcf1a2d6ebef782f9cffcd458cb016540336542","amp;dn":"%5BSynth%5D+Front+242+-+Integration+Eight+X+Ten","amp;tr":["udp%3A%2F%2Ftracker.openbittorrent.com%3A80","udp%3A%2F%2Fopen.demonii.com%3A1337","udp%3A%2F%2Ftracker.coppersurfer.tk%3A6969","udp%3A%2F%2Fexodus.desync.com%3A6969"],"infoHash":"1fcf1a2d6ebef782f9cffcd458cb016540336542","infoHashBuffer":{"type":"Buffer","data":[31,207,26,45,110,190,247,130,249,207,252,212,88,203,1,101,64,51,101,66]},"announce":[],"urlList":[]}}