{"title":"Nederlandse top 40_week04_DutchreleaseTeam","uid":6119176,"size":360098746,"categoryP":"audio","categoryS":"other","magnet":"?xt=urn:btih:2167061434594711744ac8c86959d06c0ce4dc37&amp;dn=Nederlandse+top+40_week04_DutchreleaseTeam&amp;tr=udp%3A%2F%2Ftracker.openbittorrent.com%3A80&amp;tr=udp%3A%2F%2Fopen.demonii.com%3A1337&amp;tr=udp%3A%2F%2Ftracker.coppersurfer.tk%3A6969&amp;tr=udp%3A%2F%2Fexodus.desync.com%3A6969","seeders":0,"leechers":1,"uploader":"DutchReleaseTeam","files":45,"time":1295685411,"description":"De Nederlandse top 40 week 51\n\n[img]http://t0.gstatic.com/images?q=tbn:ANd9GcSXf-B-nTP3Yzc2jhC6X1tYFEOWqxSJHaOfET-INxgd6mzANILHLw[/img]\n\n01 01 06 Martin Solveig ft. Dragonette - Hello\n02 02 07 Adele - Rolling In The Deep\n03 03 06 Bruno Mars - Grenade\n04 04 10 The Black Eyed Peas - The Time (Dirty Bit)\n05 06 18 Rihanna - Only Girl (In The World)\n06 07 11 B.o.B ft. Rivers Cuomo - Magic\n07 05 08 Lange Frans &amp; ThÃƒÂ© Lau - Zing Voor Me\n08 08 17 Bruno Mars - Just The Way You Are\n09 12 09 John Mayer - Perfectly Lonely\n10 15 11 Caro Emerald - Stuck\n11 31 02 Vaya Con Dios - Hey (Nah neh nah)\n12 14 08 David Guetta ft. Rihanna - Who\\'s That Chick\n13 13 04 P!nk - Fuckin\\' Perfect\n14 11 08 Nelly - Just A Dream\n15 10 15 Taio Cruz - Dynamite\n16 16 08 Take That - The Flood\n17 09 14 Duck Sauce - Barbra Streisand\n18 22 04 Ilse DeLange - Beautiful Distraction\n19 18 08 Jason DerÃƒÂ¼lo - What If\n20 26 03 Krystl - Golden days\n21 32 02 Enrique Iglesias ft. Ludacris - Tonight (I\\'m fuckin\\' you)\n22 19 04 Tinie Tempah ft. Eric Turner - Written In The Stars\n23 -- 01 James Blake - Limit To Your Love\n24 17 13 Far*East Movement ft. The Cataracs &amp; Dev - Like A G6\n25 20 14 P!nk - Raise Your Glass\n26 -- 01 Jan Smit - Niemand Zo Trots Als Wij\n27 23 06 Rihanna ft. Drake - What\\'s My Name\n28 21 10 New Kids ft. DJ Paul Elstak - Turbo!\n29 37 02 Far*East Movement ft. Ryan Tedder - Rocketeer\n30 30 12 Katy Perry - Firework\n31 25 07 VanVelzen - Take Me In\n32 24 03 Sick Puppies - Maybe\n33 38 02 The Script - Nothing\n34 -- 01 Taio Cruz ft. Travie McCoy - Higher\n35 28 05 Michael Jackson ft. Akon - Hold My Hand\n36 -- 01 Britney Spears - Hold it against me\n37 36 07 Nick &amp; Simon - Vlinders\n38 33 10 Travie McCoy - We\\'ll Be Alright\n39 -- 01 Scouting for Girls - Take a Chance\n40 35 16 James Blunt - Stay The Night \n\n\nDeze film wordt u aangeboden door het DutchReleaseTeam.\nVoor de reviews van de nieuwste films, muziek, series, games etc\nga dan eens naar http://www.hetmultimediacafe.nl\n\n[img]http://i556.photobucket.com/albums/ss2/jeeve2010/Headervoorupload2.png[/img]","torrent":{"xt":"urn:btih:2167061434594711744ac8c86959d06c0ce4dc37","amp;dn":"Nederlandse+top+40_week04_DutchreleaseTeam","amp;tr":["udp%3A%2F%2Ftracker.openbittorrent.com%3A80","udp%3A%2F%2Fopen.demonii.com%3A1337","udp%3A%2F%2Ftracker.coppersurfer.tk%3A6969","udp%3A%2F%2Fexodus.desync.com%3A6969"],"infoHash":"2167061434594711744ac8c86959d06c0ce4dc37","infoHashBuffer":{"type":"Buffer","data":[33,103,6,20,52,89,71,17,116,74,200,200,105,89,208,108,12,228,220,55]},"announce":[],"urlList":[]}}