{"title":"BRAZZERS TRAILER PART 003(04-09 September 2014)","uid":11456776,"size":263811952,"categoryP":"porn","categoryS":"movie_clips","magnet":"?xt=urn:btih:2abb8f0a2405439ed22225beb526979a60973a46&amp;dn=BRAZZERS+TRAILER+PART+003%2804-09+September+2014%29&amp;tr=udp%3A%2F%2Ftracker.openbittorrent.com%3A80&amp;tr=udp%3A%2F%2Fopen.demonii.com%3A1337&amp;tr=udp%3A%2F%2Ftracker.coppersurfer.tk%3A6969&amp;tr=udp%3A%2F%2Fexodus.desync.com%3A6969","seeders":0,"leechers":1,"uploader":"NETBOX68","files":23,"time":1415947628,"description":"BRAZZERS TRAILER PART 003(04-09 September 2014)\n---------------------------------------------------------------------------------------------------------------------------------------------\n &lt;a href=&quot;\nhttp://bayimg.com/IAcHdAaGm&quot; rel=&quot;nofollow&quot; target=&quot;_NEW&quot;&gt;\nhttp://bayimg.com/IAcHdAaGm&lt;/a&gt;\n\n--------------------------------------------------------------------------------------------------------------------------------------------\nTRAILER\n\nBig Tits In Uniform_What Do You Do With A Horny Sailor( Leya Falcon &amp; Marco Rivera )\nDirty Masseur_She Wants More Than a Massage( Erica Fontes &amp; Pablo Ferrari )\nBig Tits At School_College Camgirl( Anya Ivy &amp; Mick Blue )\nMommy Got Boobs_Your Darling Stepmom( Darling Danika &amp; Keiran Lee )\nDoctor Adventures_I'm Horny - Call an Ambulance!( Valentina Nappi &amp; Christian Clay )\nBig Wet Butts_Candice's Double Doggy Dare( Candice Dare &amp; Mick Blue )\nTeens Like It Big_Gingers Have No Soul( Alex Tanner &amp; Johnny Sins )\nPorn Stars Like It Big_Amazon Warrior From Dimension XXX( Lexi Lowe &amp; Ryan Ryder )\nMILFs Like It Big_Sunbathing Milf's Big Cock DP( Ava Addams , Keiran Lee &amp; Toni Ribas )\nHot And Mean_Suds and Milfs( Kianna Dior &amp; Kiara Mia )\nBaby Got Boobs_Get Her To The Girth( Karmen Karma &amp; Johnny Sins )\n\n------------------------------------------------------------------------------------------------------------------------------------------------------------------\nPICTURES\n &lt;a href=&quot;\nhttp://thepiratebay.se/torrent/11092592/BRAZZERS_PICTURES_PART_003%2804-09_September_2014%29&quot; rel=&quot;nofollow&quot; target=&quot;_NEW&quot;&gt;\nhttp://thepiratebay.se/torrent/11092592/BRAZZERS_PICTURES_PART_003%2804-09_September_2014%29&lt;/a&gt;","torrent":{"xt":"urn:btih:2abb8f0a2405439ed22225beb526979a60973a46","amp;dn":"BRAZZERS+TRAILER+PART+003%2804-09+September+2014%29","amp;tr":["udp%3A%2F%2Ftracker.openbittorrent.com%3A80","udp%3A%2F%2Fopen.demonii.com%3A1337","udp%3A%2F%2Ftracker.coppersurfer.tk%3A6969","udp%3A%2F%2Fexodus.desync.com%3A6969"],"infoHash":"2abb8f0a2405439ed22225beb526979a60973a46","infoHashBuffer":{"type":"Buffer","data":[42,187,143,10,36,5,67,158,210,34,37,190,181,38,151,154,96,151,58,70]},"announce":[],"urlList":[]}}