{"title":"Opie and Anthony 2008-09-17-O&amp;A CF64k mp3","uid":4400648,"size":102678725,"categoryP":"audio","categoryS":"other","magnet":"?xt=urn:btih:2c4c144cced3b174d1d95af28700d3664b794fd7&amp;dn=Opie+and+Anthony+2008-09-17-O%26A+CF64k+mp3&amp;tr=udp%3A%2F%2Ftracker.openbittorrent.com%3A80&amp;tr=udp%3A%2F%2Fopen.demonii.com%3A1337&amp;tr=udp%3A%2F%2Ftracker.coppersurfer.tk%3A6969&amp;tr=udp%3A%2F%2Fexodus.desync.com%3A6969","seeders":0,"leechers":1,"uploader":"mothergoose56","files":1,"time":1221675971,"description":"Opie and Anthony show CBS/XM commercial-free uncensored 64k mp3\t","torrent":{"xt":"urn:btih:2c4c144cced3b174d1d95af28700d3664b794fd7","amp;dn":"Opie+and+Anthony+2008-09-17-O%26A+CF64k+mp3","amp;tr":["udp%3A%2F%2Ftracker.openbittorrent.com%3A80","udp%3A%2F%2Fopen.demonii.com%3A1337","udp%3A%2F%2Ftracker.coppersurfer.tk%3A6969","udp%3A%2F%2Fexodus.desync.com%3A6969"],"infoHash":"2c4c144cced3b174d1d95af28700d3664b794fd7","infoHashBuffer":{"type":"Buffer","data":[44,76,20,76,206,211,177,116,209,217,90,242,135,0,211,102,75,121,79,215]},"announce":[],"urlList":[]}}