{"title":"Big.Wet.Breasts.XXX.DVDRiP.x264-PORNOLATiON","uid":9103109,"size":1936113204,"categoryP":"porn","categoryS":"movies","magnet":"?xt=urn:btih:4f7cf115dff77a6ea7dc5ec60cc98f68c1504086&amp;dn=Big.Wet.Breasts.XXX.DVDRiP.x264-PORNOLATiON&amp;tr=udp%3A%2F%2Ftracker.openbittorrent.com%3A80&amp;tr=udp%3A%2F%2Fopen.demonii.com%3A1337&amp;tr=udp%3A%2F%2Ftracker.coppersurfer.tk%3A6969&amp;tr=udp%3A%2F%2Fexodus.desync.com%3A6969","seeders":0,"leechers":0,"uploader":null,"files":1,"time":1382806752,"description":" &lt;a href=&quot;http://i.imgur.com/8E64J5U.jpg&quot; rel=&quot;nofollow&quot; target=&quot;_NEW&quot;&gt;http://i.imgur.com/8E64J5U.jpg&lt;/a&gt;","torrent":{"xt":"urn:btih:4f7cf115dff77a6ea7dc5ec60cc98f68c1504086","amp;dn":"Big.Wet.Breasts.XXX.DVDRiP.x264-PORNOLATiON","amp;tr":["udp%3A%2F%2Ftracker.openbittorrent.com%3A80","udp%3A%2F%2Fopen.demonii.com%3A1337","udp%3A%2F%2Ftracker.coppersurfer.tk%3A6969","udp%3A%2F%2Fexodus.desync.com%3A6969"],"infoHash":"4f7cf115dff77a6ea7dc5ec60cc98f68c1504086","infoHashBuffer":{"type":"Buffer","data":[79,124,241,21,223,247,122,110,167,220,94,198,12,201,143,104,193,80,64,134]},"announce":[],"urlList":[]}}