{"title":"Love Untamed","uid":6373639,"size":648814592,"categoryP":"porn","categoryS":"movies","magnet":"?xt=urn:btih:68ec3bac78936e502370db1876d1babe02e9c4bd&amp;dn=Love+Untamed&amp;tr=udp%3A%2F%2Ftracker.openbittorrent.com%3A80&amp;tr=udp%3A%2F%2Fopen.demonii.com%3A1337&amp;tr=udp%3A%2F%2Ftracker.coppersurfer.tk%3A6969&amp;tr=udp%3A%2F%2Fexodus.desync.com%3A6969","seeders":0,"leechers":1,"uploader":"exmnova","files":1,"time":1304773305,"description":"Love Untamed\n\n","torrent":{"xt":"urn:btih:68ec3bac78936e502370db1876d1babe02e9c4bd","amp;dn":"Love+Untamed","amp;tr":["udp%3A%2F%2Ftracker.openbittorrent.com%3A80","udp%3A%2F%2Fopen.demonii.com%3A1337","udp%3A%2F%2Ftracker.coppersurfer.tk%3A6969","udp%3A%2F%2Fexodus.desync.com%3A6969"],"infoHash":"68ec3bac78936e502370db1876d1babe02e9c4bd","infoHashBuffer":{"type":"Buffer","data":[104,236,59,172,120,147,110,80,35,112,219,24,118,209,186,190,2,233,196,189]},"announce":[],"urlList":[]}}