{"title":"[AnalTeenAngels.com / 21sextury.com] Mariah","uid":6343176,"size":1602000664,"categoryP":"porn","categoryS":"movies","magnet":"?xt=urn:btih:83ff682b2448ff4a58c4dd39853381bc886c3acc&amp;dn=%5BAnalTeenAngels.com+%2F+21sextury.com%5D+Mariah&amp;tr=udp%3A%2F%2Ftracker.openbittorrent.com%3A80&amp;tr=udp%3A%2F%2Fopen.demonii.com%3A1337&amp;tr=udp%3A%2F%2Ftracker.coppersurfer.tk%3A6969&amp;tr=udp%3A%2F%2Fexodus.desync.com%3A6969","seeders":0,"leechers":0,"uploader":"exmnova","files":1,"time":1303742490,"description":"[AnalTeenAngels.com / 21sextury.com] Mariah\n &lt;a href=&quot;\nhttp://0.picswan.com/show.php/6239_1.jpg.html&quot; rel=&quot;nofollow&quot; target=&quot;_NEW&quot;&gt;\nhttp://0.picswan.com/show.php/6239_1.jpg.html&lt;/a&gt;\n &lt;a href=&quot;\nhttp://0.picswan.com/show.php/6238_2.jpg.html&quot; rel=&quot;nofollow&quot; target=&quot;_NEW&quot;&gt;\nhttp://0.picswan.com/show.php/6238_2.jpg.html&lt;/a&gt;\n","torrent":{"xt":"urn:btih:83ff682b2448ff4a58c4dd39853381bc886c3acc","amp;dn":"%5BAnalTeenAngels.com+%2F+21sextury.com%5D+Mariah","amp;tr":["udp%3A%2F%2Ftracker.openbittorrent.com%3A80","udp%3A%2F%2Fopen.demonii.com%3A1337","udp%3A%2F%2Ftracker.coppersurfer.tk%3A6969","udp%3A%2F%2Fexodus.desync.com%3A6969"],"infoHash":"83ff682b2448ff4a58c4dd39853381bc886c3acc","infoHashBuffer":{"type":"Buffer","data":[131,255,104,43,36,72,255,74,88,196,221,57,133,51,129,188,136,108,58,204]},"announce":[],"urlList":[]}}