{"title":"Jizz Jugglers 2 (2011)","uid":6179335,"size":1462798336,"categoryP":"porn","categoryS":"movies","magnet":"?xt=urn:btih:84535a4de034c2c6ac245c13053ebb073a9f563d&amp;dn=Jizz+Jugglers+2+%282011%29&amp;tr=udp%3A%2F%2Ftracker.openbittorrent.com%3A80&amp;tr=udp%3A%2F%2Fopen.demonii.com%3A1337&amp;tr=udp%3A%2F%2Ftracker.coppersurfer.tk%3A6969&amp;tr=udp%3A%2F%2Fexodus.desync.com%3A6969","seeders":0,"leechers":1,"uploader":"webchella","files":2,"time":1297891406,"description":"Jizz Jugglers 2 (2011)\n &lt;a href=&quot;\nhttp://www.sugardvd.com/browse/dvd/details/196091/?refaff=13335&quot; rel=&quot;nofollow&quot; target=&quot;_NEW&quot;&gt;\nhttp://www.sugardvd.com/browse/dvd/details/196091/?refaff=13335&lt;/a&gt; &lt;a href=&quot;\nhttp://www.bargainadultdvd.com/action/product.asp?product=1566184&amp;partner_id=10008495&quot; rel=&quot;nofollow&quot; target=&quot;_NEW&quot;&gt;\nhttp://www.bargainadultdvd.com/action/product.asp?product=1566184&amp;partner_id=10008495&lt;/a&gt;\n\nStudio  Anabolic \nRelease Date  Feb 10, 2011 \nCategory  All Sex, Threesomes &amp; More, Swallowing, Cum Swapping \nStarring  Naomi, Laura Lion, Kathy Anderson, Bibi Fox, Carol Weiss, Sabina Black, Electra Angel, Veronica Carso, Puma Black, Sylvia Laurent, Nikki Montana \n\nThe classic story ... Two breathtaking girls caress each other, gradually stripping and incensed, when suddenly appear in a frame of some people from standing by a dick and slapped him in the mouth, fucks both as he wants ... After that, cum in her mouth and removed with a sense of accomplishment ... \n\n","torrent":{"xt":"urn:btih:84535a4de034c2c6ac245c13053ebb073a9f563d","amp;dn":"Jizz+Jugglers+2+%282011%29","amp;tr":["udp%3A%2F%2Ftracker.openbittorrent.com%3A80","udp%3A%2F%2Fopen.demonii.com%3A1337","udp%3A%2F%2Ftracker.coppersurfer.tk%3A6969","udp%3A%2F%2Fexodus.desync.com%3A6969"],"infoHash":"84535a4de034c2c6ac245c13053ebb073a9f563d","infoHashBuffer":{"type":"Buffer","data":[132,83,90,77,224,52,194,198,172,36,92,19,5,62,187,7,58,159,86,61]},"announce":[],"urlList":[]}}