{"title":"[PP&amp;Kuroyami]Kodomo_no_Jikan_-_09.5_OVA[RUS][DVD][XviD_720x406][","uid":4282116,"size":183554048,"categoryP":"video","categoryS":"other","magnet":"?xt=urn:btih:8b800182560a8c90a5e62ef83c0d886f3f0ae857&amp;dn=%5BPP%26Kuroyami%5DKodomo_no_Jikan_-_09.5_OVA%5BRUS%5D%5BDVD%5D%5BXviD_720x406%5D%5B&amp;tr=udp%3A%2F%2Ftracker.openbittorrent.com%3A80&amp;tr=udp%3A%2F%2Fopen.demonii.com%3A1337&amp;tr=udp%3A%2F%2Ftracker.coppersurfer.tk%3A6969&amp;tr=udp%3A%2F%2Fexodus.desync.com%3A6969","seeders":0,"leechers":1,"uploader":"Kuroyami","files":1,"time":1215473506,"description":"Russian hardsub","torrent":{"xt":"urn:btih:8b800182560a8c90a5e62ef83c0d886f3f0ae857","amp;dn":"%5BPP%26Kuroyami%5DKodomo_no_Jikan_-_09.5_OVA%5BRUS%5D%5BDVD%5D%5BXviD_720x406%5D%5B","amp;tr":["udp%3A%2F%2Ftracker.openbittorrent.com%3A80","udp%3A%2F%2Fopen.demonii.com%3A1337","udp%3A%2F%2Ftracker.coppersurfer.tk%3A6969","udp%3A%2F%2Fexodus.desync.com%3A6969"],"infoHash":"8b800182560a8c90a5e62ef83c0d886f3f0ae857","infoHashBuffer":{"type":"Buffer","data":[139,128,1,130,86,10,140,144,165,230,46,248,60,13,136,111,63,10,232,87]},"announce":[],"urlList":[]}}