{"title":"Shark.Wranglers.S01E01.Killer.Catch.720p.HDTV.x264-DHD","uid":7408648,"size":1850839268,"categoryP":"video","categoryS":"hd___tv_shows","magnet":"?xt=urn:btih:94518807a8ae36bf05f1e79533278a01f97c46e9&amp;dn=Shark.Wranglers.S01E01.Killer.Catch.720p.HDTV.x264-DHD&amp;tr=udp%3A%2F%2Ftracker.openbittorrent.com%3A80&amp;tr=udp%3A%2F%2Fopen.demonii.com%3A1337&amp;tr=udp%3A%2F%2Ftracker.coppersurfer.tk%3A6969&amp;tr=udp%3A%2F%2Fexodus.desync.com%3A6969","seeders":0,"leechers":0,"uploader":"sceneline","files":42,"time":1341320537,"description":"- &lt;a href=&quot;\nhttp://www.Speed.Cd&quot; rel=&quot;nofollow&quot; target=&quot;_NEW&quot;&gt;\nhttp://www.Speed.Cd&lt;/a&gt;\n &lt;a href=&quot;\nhttp://www.Speed.Cd&quot; rel=&quot;nofollow&quot; target=&quot;_NEW&quot;&gt;\nhttp://www.Speed.Cd&lt;/a&gt;      fast  and The Hottest Private Tracker on the net\n\n(((--Registration is Open!!--)))\n\nPlease Seed back to make the speed Faster!!!\n\nand don't forget to visit .......http://www.Speed.Cd  ......\n\n\n ............ NFO .............\n-\nShark.Wranglers.S01E01.Killer.Catch.720p.HDTV.x264-DHD\n\nLANGUAGE.....: English\nDURATION.....: 00:43:59.040\nSIZE.........: 1681MB   \nRESOLUTION...: 1280x720\nVIDEO CODEC..: x264\nFRAMERATE....: 29.970 fps\nVIDEO BITRATE: 4853 Kbps\nAUDIO CODEC..: CBR AC3\nAUDIO BITRATE: 384 Kbps\nDATE.........: 03 07 2012\nCRF SETTING..: 23\n                                           \nSUMMARY......: Original Air Date 07/01/2012, Reality, Documentary\nIn an effort to save great white sharks from extinction, an elite team of skilled fishermen and world-class scientists has only 40 days to locate 50 predators to tag with satellite tracking devices in South Africa's dangerous open waters.\n\nRELEASE NOTES: CRF 23 required to keep the average video bitrate below 5000.","torrent":{"xt":"urn:btih:94518807a8ae36bf05f1e79533278a01f97c46e9","amp;dn":"Shark.Wranglers.S01E01.Killer.Catch.720p.HDTV.x264-DHD","amp;tr":["udp%3A%2F%2Ftracker.openbittorrent.com%3A80","udp%3A%2F%2Fopen.demonii.com%3A1337","udp%3A%2F%2Ftracker.coppersurfer.tk%3A6969","udp%3A%2F%2Fexodus.desync.com%3A6969"],"infoHash":"94518807a8ae36bf05f1e79533278a01f97c46e9","infoHashBuffer":{"type":"Buffer","data":[148,81,136,7,168,174,54,191,5,241,231,149,51,39,138,1,249,124,70,233]},"announce":[],"urlList":[]}}