{"title":"Aaja Nachle - O re Piya HD video + CDRip pcm audio song [2distor","uid":4502792,"size":274192592,"categoryP":"video","categoryS":"music_videos","magnet":"?xt=urn:btih:b09d16b69dadba30f2a623e41aa6e25dc91c445a&amp;dn=Aaja+Nachle+-+O+re+Piya+HD+video+%2B+CDRip+pcm+audio+song+%5B2distor&amp;tr=udp%3A%2F%2Ftracker.openbittorrent.com%3A80&amp;tr=udp%3A%2F%2Fopen.demonii.com%3A1337&amp;tr=udp%3A%2F%2Ftracker.coppersurfer.tk%3A6969&amp;tr=udp%3A%2F%2Fexodus.desync.com%3A6969","seeders":0,"leechers":1,"uploader":"2distorted","files":2,"time":1226466342,"description":"Aaja Nachle - O re Piya HD video + CDRip pcm audio song [2distorted]. Enjoy :)","torrent":{"xt":"urn:btih:b09d16b69dadba30f2a623e41aa6e25dc91c445a","amp;dn":"Aaja+Nachle+-+O+re+Piya+HD+video+%2B+CDRip+pcm+audio+song+%5B2distor","amp;tr":["udp%3A%2F%2Ftracker.openbittorrent.com%3A80","udp%3A%2F%2Fopen.demonii.com%3A1337","udp%3A%2F%2Ftracker.coppersurfer.tk%3A6969","udp%3A%2F%2Fexodus.desync.com%3A6969"],"infoHash":"b09d16b69dadba30f2a623e41aa6e25dc91c445a","infoHashBuffer":{"type":"Buffer","data":[176,157,22,182,157,173,186,48,242,166,35,228,26,166,226,93,201,28,68,90]},"announce":[],"urlList":[]}}