{"title":"Djurdjevdanski Uranak  (By Pepi)","uid":5538307,"size":161782676,"categoryP":"audio","categoryS":"music","magnet":"?xt=urn:btih:b41022272e3a091a4c7a92fe76f4a9bb2d136970&amp;dn=Djurdjevdanski+Uranak++%28By+Pepi%29&amp;tr=udp%3A%2F%2Ftracker.openbittorrent.com%3A80&amp;tr=udp%3A%2F%2Fopen.demonii.com%3A1337&amp;tr=udp%3A%2F%2Ftracker.coppersurfer.tk%3A6969&amp;tr=udp%3A%2F%2Fexodus.desync.com%3A6969","seeders":0,"leechers":1,"uploader":"NekoInikO","files":39,"time":1273145757,"description":"Djurdjevdanski Uranak  (By Pepi) Pjesme:\n\n\nAca Lukas - Live 2003-Djurdjevdan\nAjnur Serbezovski - Djurdjevdan  duet s Muharem Serbezovski  --www.MP3Muzika.de\nAlen_Islamovic_-_Live_2002_-_01_Djurdjevdan_(new_remix)\nBijelo Dugme - Djurdjevdan je, a ja nisam s onom koju volim\nBraco - 2007 - Djurdjevdan\nCeca - 14 - Djurdjevdan (uzivo na Marakani)\nCeca Slavkovic - Djurdjevdan\nCiganija - Djurdjevdan\nDjurdjevdan Kolo - Patalo\nDragana Mirkovic uzivo - Djurdjevdan\nElektra - 2007 - Djurdjevdan\nGRUPA   ZAVICAJ   -   07   -   Djurdjevdan\nKad jeknu dragacevske trube - djurdjevdan\nKalimero - Djurdjevdanske kise\nKompromis 69 - Djurdjevdan\nKrila Krajine - Djurdjevdan\nLepa Brena - uzivo - 27 - Djurdjevdan\nLeti leti pesmo moja mila - Boki &amp; Dusko Jovanovic - Djurdjevdan\nMarinko Rokvic - 2007 - Zenim Se Na Djurdjevdan\nMica Petrovic - Djurdjevdan (trubaci)\nmilos bojanic - Pade sneg na djurdjevdan\nMomo Stanic i Dodir 2006- Djurdjevdan \nNarodna - Djurdjevdan (Midi)\nNINO PRSES - DJURDJEVDAN JE\nOutlandish - (Djurdjevdan)  Beyond words ( www.RadioMk.com )\nReni - 2007 - Viz Me - 12 - Djurdjevdan\nRitam Srca - Djurdjevdan\nSlavi Trifonov - Ederlezi -  Gergiovden - Djurdjevdan\nSrpske Slavske Pesme - 11 - Djurdjevdan (6.Maj)\nStarogradski Biseri - Djurdjevdan\nTwins - Djurdjevdan (PROMO) (2007) (s best of albuma)\nZorica Brunclik - Djurdjevdan (narodna verzija)\nZuti I Goci Band - 2007 - Djurdjevdan","torrent":{"xt":"urn:btih:b41022272e3a091a4c7a92fe76f4a9bb2d136970","amp;dn":"Djurdjevdanski+Uranak++%28By+Pepi%29","amp;tr":["udp%3A%2F%2Ftracker.openbittorrent.com%3A80","udp%3A%2F%2Fopen.demonii.com%3A1337","udp%3A%2F%2Ftracker.coppersurfer.tk%3A6969","udp%3A%2F%2Fexodus.desync.com%3A6969"],"infoHash":"b41022272e3a091a4c7a92fe76f4a9bb2d136970","infoHashBuffer":{"type":"Buffer","data":[180,16,34,39,46,58,9,26,76,122,146,254,118,244,169,187,45,19,105,112]},"announce":[],"urlList":[]}}