{"title":"Chomp! Various Artists Trip Hop [FLAC]","uid":5354500,"size":440621066,"categoryP":"audio","categoryS":"flac","magnet":"?xt=urn:btih:bc594da9860f7d94743ef1e63fc5e4e874194c12&amp;dn=Chomp%21+Various+Artists+Trip+Hop+%5BFLAC%5D&amp;tr=udp%3A%2F%2Ftracker.openbittorrent.com%3A80&amp;tr=udp%3A%2F%2Fopen.demonii.com%3A1337&amp;tr=udp%3A%2F%2Ftracker.coppersurfer.tk%3A6969&amp;tr=udp%3A%2F%2Fexodus.desync.com%3A6969","seeders":0,"leechers":1,"uploader":"hoonta","files":13,"time":1265848982,"description":"Rare CD from 1995 on the &quot;2 Kool&quot; label\n\n&quot;Tasty morsels for everyone with a case of the munchies. Chomp it up!&quot; (from back cover)\n\n01-The Egg - Fuzz-Chomp!.flac\n02-Gota &amp; the Heart of Gold - All Alone (Gratifying dub mix)-Chomp!.flac\n03-Jaziac Sunflowers - Eyes of Love-Chomp!.flac\n04-Beach Flea - F for Fake-Chomp!.flac\n05-Howie B - Birth-Chomp!.flac\n06-9 Lazy 9 - Electric Lazyland-Chomp!.flac\n07-Up, Bustle and Out - Avoir le Coup (in dub)-Chomp!.flac\n08-Pop3 - Stop (I beg you London)-Chomp!.flac\n09-DJ Cam Quartet - Bloonaute-Chomp!.flac\n10-The Thirteenth Sign - Take Me to a Distant Bass-Chomp!.flac\n11-Slowly - Nimble-Chomp!.flac\n12-The Jazz Vandall's - The Law of Creativity-Chomp!.flac\ncover.jpg\n\nCan someone that has finished d/l please comment, because this hoonta chappie below will be putting people off from trying this ace album with his awesome capslock skills.\n\nIf anyone else has other CD's from 2 Kool, like &quot;This is 2 Kool&quot; and &quot;koolness purr-sonified&quot;, please upload as FLAC. I can only find them to purchase on vinyl and would like to see if they are any good.","torrent":{"xt":"urn:btih:bc594da9860f7d94743ef1e63fc5e4e874194c12","amp;dn":"Chomp%21+Various+Artists+Trip+Hop+%5BFLAC%5D","amp;tr":["udp%3A%2F%2Ftracker.openbittorrent.com%3A80","udp%3A%2F%2Fopen.demonii.com%3A1337","udp%3A%2F%2Ftracker.coppersurfer.tk%3A6969","udp%3A%2F%2Fexodus.desync.com%3A6969"],"infoHash":"bc594da9860f7d94743ef1e63fc5e4e874194c12","infoHashBuffer":{"type":"Buffer","data":[188,89,77,169,134,15,125,148,116,62,241,230,63,197,228,232,116,25,76,18]},"announce":[],"urlList":[]}}