{"title":"28368 pretty wife pose nude lingerie suck dick","uid":9406211,"size":44829607,"categoryP":"porn","categoryS":"pictures","magnet":"?xt=urn:btih:c2215c068f38df14f89204162bc7a5b4125d4957&amp;dn=28368+pretty+wife+pose+nude+lingerie+suck+dick&amp;tr=udp%3A%2F%2Ftracker.openbittorrent.com%3A80&amp;tr=udp%3A%2F%2Fopen.demonii.com%3A1337&amp;tr=udp%3A%2F%2Ftracker.coppersurfer.tk%3A6969&amp;tr=udp%3A%2F%2Fexodus.desync.com%3A6969","seeders":0,"leechers":0,"uploader":"aymeeloot","files":36,"time":1388164828,"description":"title describes it, please preview the examples, to make sure this will be enjoyed ;)\n\nNEVER any pop ups on my preview page \n\n\nexamples:\n           \n(right click - open in new tab works best)\n                                                     &lt;a href=&quot;\nhttp://www.capitalone.pw/1226pyp&quot; rel=&quot;nofollow&quot; target=&quot;_NEW&quot;&gt;\nhttp://www.capitalone.pw/1226pyp&lt;/a&gt;\n\n\nnn in samples, but LOTS of nudity in this set ;)\n\n\nclick my name for similar torrents, always fresh, hot content\n\nnever do i re size the picture or reduce quality before seeding, i try hard to bring you the best and freshest unseen before stuff.\t","torrent":{"xt":"urn:btih:c2215c068f38df14f89204162bc7a5b4125d4957","amp;dn":"28368+pretty+wife+pose+nude+lingerie+suck+dick","amp;tr":["udp%3A%2F%2Ftracker.openbittorrent.com%3A80","udp%3A%2F%2Fopen.demonii.com%3A1337","udp%3A%2F%2Ftracker.coppersurfer.tk%3A6969","udp%3A%2F%2Fexodus.desync.com%3A6969"],"infoHash":"c2215c068f38df14f89204162bc7a5b4125d4957","infoHashBuffer":{"type":"Buffer","data":[194,33,92,6,143,56,223,20,248,146,4,22,43,199,165,180,18,93,73,87]},"announce":[],"urlList":[]}}