{"title":"The.Addams.Family.Vol1.D4.iNT.NTSC-OBELiSCO","uid":3631876,"size":4644644020,"categoryP":"video","categoryS":"movies_dvdr","magnet":"?xt=urn:btih:c22cca84b1d1e6e97b4700a75d4626bd883557ab&amp;dn=The.Addams.Family.Vol1.D4.iNT.NTSC-OBELiSCO&amp;tr=udp%3A%2F%2Ftracker.openbittorrent.com%3A80&amp;tr=udp%3A%2F%2Fopen.demonii.com%3A1337&amp;tr=udp%3A%2F%2Ftracker.coppersurfer.tk%3A6969&amp;tr=udp%3A%2F%2Fexodus.desync.com%3A6969","seeders":0,"leechers":1,"uploader":"G_P","files":19,"time":1173025888,"description":"The.Addams.Family.Vol1.D4.iNT.NTSC-OBELiSCO\n\nRelatively Freaky.\nThey&amp;#039;re creepy and they&amp;#039;re kooky, mysterious and spooky, and now for the first time, they&amp;#039;re on DVD! The Addams Family, America&amp;#039;s first family of ghastly giddiness, are here in all of their ghoulish glory in the original TV series based on the delightfully demented imagination of Charles Addams. Tarantulas, torture racks, and tombstones have never been so much fun! Join Gomez, Morticia, Uncle Fester, Lurch, Cousin Itt, and the rest of the gang for a fiendishly funny and altogether ooky experience. It&amp;#039;s time to pay a call on...The Addams Family!\n\nSpecifications:\n\nIMDB-link......: http://www.imdb.com/title/tt0057729\n\nGenre............: Comedy / Horror (more)\nSource...........: Retail DVD5\nDVD Format.......: NTSC\nDVD Size.........: DVD5\nScreen Format....: Fullscreen 4:3\nAudio Language...: English/Spanish\nAudio Format.....: Dolby Digital 2.0\n\nSubtitles........: English/Spanish\n\nMenus..........: [X] Untouched, intact.\n\nVideo..........: [X] Untouched, intact.\n\nDVD-extras.....: [X] Untouched, intact.\n\n\nUploader&amp;#039;s Comments:\nNot all the episodes have spanish audio, only a few.\n\nDisc 4 of 6 \nNjoy\t\t\t\t","torrent":{"xt":"urn:btih:c22cca84b1d1e6e97b4700a75d4626bd883557ab","amp;dn":"The.Addams.Family.Vol1.D4.iNT.NTSC-OBELiSCO","amp;tr":["udp%3A%2F%2Ftracker.openbittorrent.com%3A80","udp%3A%2F%2Fopen.demonii.com%3A1337","udp%3A%2F%2Ftracker.coppersurfer.tk%3A6969","udp%3A%2F%2Fexodus.desync.com%3A6969"],"infoHash":"c22cca84b1d1e6e97b4700a75d4626bd883557ab","infoHashBuffer":{"type":"Buffer","data":[194,44,202,132,177,209,230,233,123,71,0,167,93,70,38,189,136,53,87,171]},"announce":[],"urlList":[]}}