{"title":"Anthony Kaun Hai 2006.avi","uid":6472200,"size":739383296,"categoryP":"video","categoryS":"movies","magnet":"?xt=urn:btih:d436e50043e5cf3999e4ccb5451e93d0d207185d&amp;dn=Anthony+Kaun+Hai+2006.avi&amp;tr=udp%3A%2F%2Ftracker.openbittorrent.com%3A80&amp;tr=udp%3A%2F%2Fopen.demonii.com%3A1337&amp;tr=udp%3A%2F%2Ftracker.coppersurfer.tk%3A6969&amp;tr=udp%3A%2F%2Fexodus.desync.com%3A6969","seeders":0,"leechers":1,"uploader":"shan01","files":-1,"time":1308179266,"description":"Star Cast\nSanjay Dutt...... Master Madan\nArshad Warsi...... Champ\nMinissha Lamba...... Jiya\nAnousha Dandekar...... Rosa\nRaghuveer Yadav...... Magician Raghu Sharma\nGulshan Grover...... Detective Suraj Singh\nNaina Dhaliwal\nRavi Baswani\nChetan Hansraj\n","torrent":{"xt":"urn:btih:d436e50043e5cf3999e4ccb5451e93d0d207185d","amp;dn":"Anthony+Kaun+Hai+2006.avi","amp;tr":["udp%3A%2F%2Ftracker.openbittorrent.com%3A80","udp%3A%2F%2Fopen.demonii.com%3A1337","udp%3A%2F%2Ftracker.coppersurfer.tk%3A6969","udp%3A%2F%2Fexodus.desync.com%3A6969"],"infoHash":"d436e50043e5cf3999e4ccb5451e93d0d207185d","infoHashBuffer":{"type":"Buffer","data":[212,54,229,0,67,229,207,57,153,228,204,181,69,30,147,208,210,7,24,93]},"announce":[],"urlList":[]}}