{"title":"Prince Of Persia - The Sands of time DVDRIP ~PINKHONEY0269~","uid":5991944,"size":1311844424,"categoryP":"video","categoryS":"movies","magnet":"?xt=urn:btih:d4bc72269dc02402c5589381983a21a48605cd9a&amp;dn=Prince+Of+Persia+-+The+Sands+of+time+DVDRIP+%7EPINKHONEY0269%7E&amp;tr=udp%3A%2F%2Ftracker.openbittorrent.com%3A80&amp;tr=udp%3A%2F%2Fopen.demonii.com%3A1337&amp;tr=udp%3A%2F%2Ftracker.coppersurfer.tk%3A6969&amp;tr=udp%3A%2F%2Fexodus.desync.com%3A6969","seeders":0,"leechers":1,"uploader":"Pinkhoney0269","files":1,"time":1290914617,"description":"Run Time: 116 Minutes\n\nStarring:\n\nJake Gyllenhaal\nBen Kingsley\nGemma Arterton\nAlfred Molina\n\nA young fugitive prince and princess must stop a villain who unknowingly threatens to destroy the world with a special dagger that enables the magic sand inside to reverse time. \n\n","torrent":{"xt":"urn:btih:d4bc72269dc02402c5589381983a21a48605cd9a","amp;dn":"Prince+Of+Persia+-+The+Sands+of+time+DVDRIP+%7EPINKHONEY0269%7E","amp;tr":["udp%3A%2F%2Ftracker.openbittorrent.com%3A80","udp%3A%2F%2Fopen.demonii.com%3A1337","udp%3A%2F%2Ftracker.coppersurfer.tk%3A6969","udp%3A%2F%2Fexodus.desync.com%3A6969"],"infoHash":"d4bc72269dc02402c5589381983a21a48605cd9a","infoHashBuffer":{"type":"Buffer","data":[212,188,114,38,157,192,36,2,197,88,147,129,152,58,33,164,134,5,205,154]},"announce":[],"urlList":[]}}