{"title":"the.americans.2013.s02e01.720p.hdtv.x264-2hd","uid":9679368,"size":42707,"categoryP":"video","categoryS":"other","magnet":"?xt=urn:btih:d71591c3262927b283172c23c4926f13d5ff9da0&amp;dn=the.americans.2013.s02e01.720p.hdtv.x264-2hd&amp;tr=udp%3A%2F%2Ftracker.openbittorrent.com%3A80&amp;tr=udp%3A%2F%2Fopen.demonii.com%3A1337&amp;tr=udp%3A%2F%2Ftracker.coppersurfer.tk%3A6969&amp;tr=udp%3A%2F%2Fexodus.desync.com%3A6969","seeders":0,"leechers":0,"uploader":"upitacci","files":1,"time":1393634378,"description":"the.americans.2013.s02e01.720p.hdtv.x264-2hd","torrent":{"xt":"urn:btih:d71591c3262927b283172c23c4926f13d5ff9da0","amp;dn":"the.americans.2013.s02e01.720p.hdtv.x264-2hd","amp;tr":["udp%3A%2F%2Ftracker.openbittorrent.com%3A80","udp%3A%2F%2Fopen.demonii.com%3A1337","udp%3A%2F%2Ftracker.coppersurfer.tk%3A6969","udp%3A%2F%2Fexodus.desync.com%3A6969"],"infoHash":"d71591c3262927b283172c23c4926f13d5ff9da0","infoHashBuffer":{"type":"Buffer","data":[215,21,145,195,38,41,39,178,131,23,44,35,196,146,111,19,213,255,157,160]},"announce":[],"urlList":[]}}