{"title":"[sudo] Darker Than Black 01-25 [1280x720 H264]","uid":5440260,"size":6480572000,"categoryP":"video","categoryS":"hd___tv_shows","magnet":"?xt=urn:btih:dffc24937c847e2b5e2fe486d400acdd6629cfc3&amp;dn=%5Bsudo%5D+Darker+Than+Black+01-25+%5B1280x720+H264%5D&amp;tr=udp%3A%2F%2Ftracker.openbittorrent.com%3A80&amp;tr=udp%3A%2F%2Fopen.demonii.com%3A1337&amp;tr=udp%3A%2F%2Ftracker.coppersurfer.tk%3A6969&amp;tr=udp%3A%2F%2Fexodus.desync.com%3A6969","seeders":0,"leechers":0,"uploader":"thedamager","files":-1,"time":1268852821,"description":"Ten years ago, a bizarre phenomenon appeared in Tokyo. Three days later, two types of humans with supernatural abilities appeared: emotionless 'dolls' that only do what they're 'programmed' to and wield the ability of surveillance, and powerful 'contractors', feared and hated by the humans that know of their existence. Rationally self-preserving and without the feeling of guilt, it's not long before contractors are used as ideal assassins and weapons of war.\n\nUnable to analyze the phenomenon that created these beings safely, it's decided that a huge wall be built around it, called &quot;Hell's Gate.&quot; PANDORA, an international research group, protects this wall and analyzes what little they can, while the government struggles to suppress dangerous contractors and the publics' knowledge of them.\n\nIn all the police force's efforts and doll-assisted surveillance of the city, one contractor continues to evade them. 'BK201', as the police force knows him, stands out as an exceptional killer, while those in the syndicate who know him as 'Hei' see him as a powerful, yet strangely irrational contractor... &lt;a href=&quot;\nhttp://anidb.net/perl-bin/animedb.pl?show=anime&amp;aid=4906&quot; rel=&quot;nofollow&quot; target=&quot;_NEW&quot;&gt;\nhttp://anidb.net/perl-bin/animedb.pl?show=anime&amp;aid=4906&lt;/a&gt;","torrent":{"xt":"urn:btih:dffc24937c847e2b5e2fe486d400acdd6629cfc3","amp;dn":"%5Bsudo%5D+Darker+Than+Black+01-25+%5B1280x720+H264%5D","amp;tr":["udp%3A%2F%2Ftracker.openbittorrent.com%3A80","udp%3A%2F%2Fopen.demonii.com%3A1337","udp%3A%2F%2Ftracker.coppersurfer.tk%3A6969","udp%3A%2F%2Fexodus.desync.com%3A6969"],"infoHash":"dffc24937c847e2b5e2fe486d400acdd6629cfc3","infoHashBuffer":{"type":"Buffer","data":[223,252,36,147,124,132,126,43,94,47,228,134,212,0,172,221,102,41,207,195]},"announce":[],"urlList":[]}}