{"title":"The.Voyage.of.theDawn.Treader.2010.R5.LiNE.XviD-TiMPE","uid":6120456,"size":1475449597,"categoryP":"video","categoryS":"movies","magnet":"?xt=urn:btih:e09ca43a89bf27b585093a696f919b585e4472e9&amp;dn=The.Voyage.of.theDawn.Treader.2010.R5.LiNE.XviD-TiMPE&amp;tr=udp%3A%2F%2Ftracker.openbittorrent.com%3A80&amp;tr=udp%3A%2F%2Fopen.demonii.com%3A1337&amp;tr=udp%3A%2F%2Ftracker.coppersurfer.tk%3A6969&amp;tr=udp%3A%2F%2Fexodus.desync.com%3A6969","seeders":0,"leechers":0,"uploader":".BONE.","files":3,"time":1295721936,"description":"Source: R5 DV9\nSize: 1.37 GB | 1CD\nGenre: Adventure | Family | Fantasy\nVideo: 720 x 400, 1537Kbps, 25.000Fps\nAudio: English, 256kbps, AC3 LiNE\n\nSubs: N/A\nIMDB Rating: 6.7/10 (9,397 votes)\nRT Critics: 6.2/10 (24 reviews)\nDirected By: Michael Apted\nStarring: Ben Barnes, Skandar Keynes and Georgie Henley","torrent":{"xt":"urn:btih:e09ca43a89bf27b585093a696f919b585e4472e9","amp;dn":"The.Voyage.of.theDawn.Treader.2010.R5.LiNE.XviD-TiMPE","amp;tr":["udp%3A%2F%2Ftracker.openbittorrent.com%3A80","udp%3A%2F%2Fopen.demonii.com%3A1337","udp%3A%2F%2Ftracker.coppersurfer.tk%3A6969","udp%3A%2F%2Fexodus.desync.com%3A6969"],"infoHash":"e09ca43a89bf27b585093a696f919b585e4472e9","infoHashBuffer":{"type":"Buffer","data":[224,156,164,58,137,191,39,181,133,9,58,105,111,145,155,88,94,68,114,233]},"announce":[],"urlList":[]}}