{"title":"Eugenia [Yeviygenya] Diordiychuk Ultimate Pack (Videos and Sets)","uid":11578376,"size":750886999,"categoryP":"porn","categoryS":"pictures","magnet":"?xt=urn:btih:e311a2fcfecaae9f7856418fcf67f85cf1f0358e&amp;dn=Eugenia+%5BYeviygenya%5D+Diordiychuk+Ultimate+Pack+%28Videos+and+Sets%29&amp;tr=udp%3A%2F%2Ftracker.openbittorrent.com%3A80&amp;tr=udp%3A%2F%2Fopen.demonii.com%3A1337&amp;tr=udp%3A%2F%2Ftracker.coppersurfer.tk%3A6969&amp;tr=udp%3A%2F%2Fexodus.desync.com%3A6969","seeders":0,"leechers":2,"uploader":"ighorwho","files":20,"time":1417100844,"description":"All of Eugenias's videos and photosets I could find on Playboy official site","torrent":{"xt":"urn:btih:e311a2fcfecaae9f7856418fcf67f85cf1f0358e","amp;dn":"Eugenia+%5BYeviygenya%5D+Diordiychuk+Ultimate+Pack+%28Videos+and+Sets%29","amp;tr":["udp%3A%2F%2Ftracker.openbittorrent.com%3A80","udp%3A%2F%2Fopen.demonii.com%3A1337","udp%3A%2F%2Ftracker.coppersurfer.tk%3A6969","udp%3A%2F%2Fexodus.desync.com%3A6969"],"infoHash":"e311a2fcfecaae9f7856418fcf67f85cf1f0358e","infoHashBuffer":{"type":"Buffer","data":[227,17,162,252,254,202,174,159,120,86,65,143,207,103,248,92,241,240,53,142]},"announce":[],"urlList":[]}}