{"title":"Estigma_skateboards_1#_video(full lenght low quality)_.mp4","uid":6040069,"size":624476406,"categoryP":"video","categoryS":"movies","magnet":"?xt=urn:btih:e67da910d1a1a0e0b45f37bbcebba4fca8e8aeef&amp;dn=Estigma_skateboards_1%23_video%28full+lenght+low+quality%29_.mp4&amp;tr=udp%3A%2F%2Ftracker.openbittorrent.com%3A80&amp;tr=udp%3A%2F%2Fopen.demonii.com%3A1337&amp;tr=udp%3A%2F%2Ftracker.coppersurfer.tk%3A6969&amp;tr=udp%3A%2F%2Fexodus.desync.com%3A6969","seeders":0,"leechers":0,"uploader":"Estigma","files":1,"time":1292355468,"description":"vdeo da Estigma para divulgaÃƒÂ§ao entrea galera(breve sai um com melhor qualidade)","torrent":{"xt":"urn:btih:e67da910d1a1a0e0b45f37bbcebba4fca8e8aeef","amp;dn":"Estigma_skateboards_1%23_video%28full+lenght+low+quality%29_.mp4","amp;tr":["udp%3A%2F%2Ftracker.openbittorrent.com%3A80","udp%3A%2F%2Fopen.demonii.com%3A1337","udp%3A%2F%2Ftracker.coppersurfer.tk%3A6969","udp%3A%2F%2Fexodus.desync.com%3A6969"],"infoHash":"e67da910d1a1a0e0b45f37bbcebba4fca8e8aeef","infoHashBuffer":{"type":"Buffer","data":[230,125,169,16,209,161,160,224,180,95,55,187,206,187,164,252,168,232,174,239]},"announce":[],"urlList":[]}}